count_tokens/__init__.py
count_tokens/count.py
count_tokens-0.7.3.dist-info/METADATA
count_tokens-0.7.3.dist-info/WHEEL
count_tokens-0.7.3.dist-info/entry_points.txt
count_tokens-0.7.3.dist-info/RECORD
