Metadata-Version: 2.3
Name: count-tokens
Version: 0.7.3
Summary: Count number of tokens in the text file using tiktoken tokenizer from OpenAI.
License: MIT
Keywords: count,tokens,tiktoken,openai,tokenizer
Author: Krystian Safjan
Author-email: ksafjan@gmail.com
Requires-Python: >=3.9,<4.0
Classifier: Development Status :: 4 - Beta
Classifier: Environment :: Console
Classifier: Intended Audience :: Developers
Classifier: License :: OSI Approved :: MIT License
Classifier: Operating System :: OS Independent
Classifier: Programming Language :: Python :: 3
Classifier: Programming Language :: Python :: 3.9
Classifier: Programming Language :: Python :: 3.10
Classifier: Programming Language :: Python :: 3.11
Classifier: Programming Language :: Python :: 3.12
Classifier: Programming Language :: Python :: 3.13
Classifier: Topic :: Software Development :: Libraries :: Python Modules
Classifier: Topic :: Utilities
Requires-Dist: tiktoken (>=0.9.0,<0.10.0)
Project-URL: Documentation, https://github.com/izikeros/count_tokens
Project-URL: Homepage, https://github.com/izikeros/count_tokens
Project-URL: Repository, https://github.com/izikeros/count_tokens
